easylimit/__init__.py
easylimit/py.typed
easylimit/rate_limiter.py
easylimit-0.3.4.dist-info/METADATA
easylimit-0.3.4.dist-info/WHEEL
easylimit-0.3.4.dist-info/licenses/LICENSE
easylimit-0.3.4.dist-info/RECORD
