Metadata-Version: 2.4
Name: easylimit
Version: 0.3.4
Summary: A simple, precise Python rate limiter with built-in context manager support for hassle-free API throttling
Project-URL: Homepage, https://github.com/man8/easylimit
Project-URL: Repository, https://github.com/man8/easylimit
Project-URL: Issues, https://github.com/man8/easylimit/issues
Author-email: Louis Mandelstam <louis@man8.com>
License-Expression: MIT
License-File: LICENSE
Keywords: api,context-manager,rate-limiting,throttling,token-bucket
Classifier: Development Status :: 4 - Beta
Classifier: Intended Audience :: Developers
Classifier: License :: OSI Approved :: MIT License
Classifier: Programming Language :: Python :: 3
Classifier: Programming Language :: Python :: 3.8
Classifier: Programming Language :: Python :: 3.9
Classifier: Programming Language :: Python :: 3.10
Classifier: Programming Language :: Python :: 3.11
Classifier: Programming Language :: Python :: 3.12
Classifier: Programming Language :: Python :: 3.13
Classifier: Topic :: Internet :: WWW/HTTP
Classifier: Topic :: Software Development :: Libraries :: Python Modules
Classifier: Topic :: System :: Networking
Requires-Python: >=3.8
Provides-Extra: dev
Requires-Dist: mypy>=1.0.0; extra == 'dev'
Requires-Dist: pytest-asyncio>=0.21.0; extra == 'dev'
Requires-Dist: pytest-cov>=4.0.0; extra == 'dev'
Requires-Dist: pytest>=7.0.0; extra == 'dev'
Requires-Dist: requests>=2.25.0; extra == 'dev'
Requires-Dist: ruff>=0.1.0; extra == 'dev'
